eelx/__init__.py
eelx/__main__.py
eelx/browsers.py
eelx/chrome.py
eelx/edge.py
eelx/electron.py
eelx/py.typed
eelx/types.py
Eelx-0.16.0.dist-info/LICENSE
Eelx-0.16.0.dist-info/METADATA
Eelx-0.16.0.dist-info/WHEEL
Eelx-0.16.0.dist-info/top_level.txt
Eelx-0.16.0.dist-info/RECORD
