Metadata-Version: 2.1
Name: Eelx
Version: 0.16.0
Summary: For little HTML GUI applications, with easy Python/JS interop
Home-page: https://github.com/gurjarms/eel
Author: Gurjar mahi
Author-email: python-eel@protonmail.com
Keywords: gui,html,javascript,electron
Classifier: Development Status :: 3 - Alpha
Classifier: Natural Language :: English
Classifier: Operating System :: MacOS
Classifier: Operating System :: POSIX
Classifier: Operating System :: Microsoft :: Windows :: Windows 10
Classifier: Programming Language :: Python :: 3
Classifier: Programming Language :: Python :: 3.7
Classifier: Programming Language :: Python :: 3.8
Classifier: Programming Language :: Python :: Implementation :: CPython
Classifier: License :: OSI Approved :: MIT License
Requires-Python: >=3.7
License-File: LICENSE
Requires-Dist: bottle
Requires-Dist: bottle-websocket
Requires-Dist: future
Requires-Dist: pyparsing
Requires-Dist: whichcraft
Provides-Extra: jinja2
Requires-Dist: jinja2 >=2.10 ; extra == 'jinja2'
